odoo/addons/purchase_tag/README.rst
odoo/addons/purchase_tag/__init__.py
odoo/addons/purchase_tag/__manifest__.py
odoo/addons/purchase_tag/i18n/purchase_tag.pot
odoo/addons/purchase_tag/models/__init__.py
odoo/addons/purchase_tag/models/purchase_order.py
odoo/addons/purchase_tag/models/purchase_tag.py
odoo/addons/purchase_tag/readme/CONTRIBUTORS.rst
odoo/addons/purchase_tag/readme/DESCRIPTION.rst
odoo/addons/purchase_tag/readme/USAGE.rst
odoo/addons/purchase_tag/security/ir.model.access.csv
odoo/addons/purchase_tag/static/description/icon.png
odoo/addons/purchase_tag/static/description/index.html
odoo/addons/purchase_tag/views/purchase_tag_view.xml
odoo/addons/purchase_tag/views/purchase_view.xml
odoo14_addon_purchase_tag-14.0.1.0.1.dist-info/METADATA
odoo14_addon_purchase_tag-14.0.1.0.1.dist-info/WHEEL
odoo14_addon_purchase_tag-14.0.1.0.1.dist-info/top_level.txt
odoo14_addon_purchase_tag-14.0.1.0.1.dist-info/RECORD
